naya/__init__.py
naya/json.py
naya-1.1.1.dist-info/LICENSE
naya-1.1.1.dist-info/METADATA
naya-1.1.1.dist-info/WHEEL
naya-1.1.1.dist-info/top_level.txt
naya-1.1.1.dist-info/RECORD
